maybe_type/__init__.py
maybe_type/main.py
maybe_type-1.0.5.dist-info/METADATA
maybe_type-1.0.5.dist-info/WHEEL
maybe_type-1.0.5.dist-info/licenses/LICENSE
maybe_type-1.0.5.dist-info/RECORD
