Metadata-Version: 2.1
Name: maybe-type
Version: 1.0.5
Summary: Addind the maybe type to python
Author: Leander
License-File: LICENSE
Classifier: Operating System :: OS Independent
Classifier: Programming Language :: Python :: 3
Requires-Python: >=3.7
